{
  "run_id": "h1only_20241001_20241231",
  "overall": "PASS",
  "exit_code": 0,
  "warnings_present": false,
  "headline_pnl_usd": 587.0,
  "live_proximal_headline_usd": 587.0,
  "study_fifty_pct_headline_usd": 0.0,
  "content_hash": "446456b301cc56ef8219c2636f9fb9186309293de067aabf12b05c3e31982499",
  "condition_counts": {},
  "event_counts": {
    "ob_seen": 239,
    "alert": 370,
    "ob_mitigated": 166,
    "re_arm": 194,
    "ob_aged_out": 59,
    "trade_exit": 188,
    "trade_fill": 126
  },
  "outcome_counts": {
    "ALERT": 311,
    "RE_ARM_WAIT": 2436,
    "OUT_OF_RANGE": 755,
    "NO_ZONE": 1038
  },
  "gates": [
    {
      "id": "G1",
      "description": "Sum pnl_usd == Sum r_realised*risk, and equals reporting headline",
      "threshold": "rel_tol 1e-09",
      "observed": {
        "headline_usd": 587.0,
        "reported": 587.0,
        "row_mismatches": 0
      },
      "verdict": "PASS"
    },
    {
      "id": "G2",
      "description": "scan records == expected (pair x walk bars); zero HEARTBEAT_GAP; never vacuous (0 declared bars with trades present = blind run)",
      "threshold": "exact, non-vacuous",
      "observed": {
        "expected": 4540,
        "actual": 4540,
        "missing_by_pair": {},
        "vacuous": false
      },
      "verdict": "PASS"
    },
    {
      "id": "G3",
      "description": "ob<=bos<alert<=fill on every filled trade (fill on the alert candle allowed)",
      "threshold": "strict inequalities",
      "observed": {
        "violations": 0,
        "sample": []
      },
      "verdict": "PASS"
    },
    {
      "id": "G4",
      "description": "every FAIL-severity condition counter is 0",
      "threshold": "== 0",
      "observed": "none",
      "verdict": "PASS"
    },
    {
      "id": "G5",
      "description": "every knob re-read at END equals manifest (no drift)",
      "threshold": "exact",
      "observed": "none",
      "verdict": "PASS"
    },
    {
      "id": "G6",
      "description": "headline recomputed from r_realised only; tp1/tp2 excluded",
      "threshold": "independent recompute",
      "observed": {
        "realised_headline": 587.0,
        "tp2_headline_for_contrast": 8740.5
      },
      "verdict": "PASS"
    },
    {
      "id": "G7",
      "description": "content hash of scan_log + events recorded for re-run compare",
      "threshold": "recorded",
      "observed": "446456b301cc56ef8219c2636f9fb9186309293de067aabf12b05c3e31982499",
      "verdict": "PASS"
    },
    {
      "id": "G8",
      "description": "NAN_ATR_SKIP <= 1% post-warmup per pair (WARN >1%, FAIL >5%)",
      "threshold": "<=1% warn, >5% fail",
      "observed": {
        "EURUSD": 0.0,
        "USDJPY": 0.0,
        "GOLD": 0.0
      },
      "verdict": "PASS"
    },
    {
      "id": "G9",
      "description": "every record validated against SCHEMA.md (ts/tz/outcome)",
      "threshold": "0 schema FAILs",
      "observed": 0,
      "verdict": "PASS"
    },
    {
      "id": "G10",
      "description": "per-trade metrics physically possible (no fake excursions)",
      "threshold": "0 violations",
      "observed": {
        "violations": 0,
        "sample": []
      },
      "verdict": "PASS"
    }
  ]
}